odoo/addons/l10n_nl_openkvk/README.rst
odoo/addons/l10n_nl_openkvk/__init__.py
odoo/addons/l10n_nl_openkvk/__manifest__.py
odoo/addons/l10n_nl_openkvk/examples/openkvk_560487.json
odoo/addons/l10n_nl_openkvk/examples/openkvk_56048785.json
odoo/addons/l10n_nl_openkvk/examples/openkvk_hoofdvestiging-56048785-0000-onestein-bv.json
odoo/addons/l10n_nl_openkvk/examples/openkvk_rechtspersoon-56048785-onestein-bv.json
odoo/addons/l10n_nl_openkvk/i18n/l10n_nl_openkvk.pot
odoo/addons/l10n_nl_openkvk/models/__init__.py
odoo/addons/l10n_nl_openkvk/models/l10n_nl_kvk_api_handler.py
odoo/addons/l10n_nl_openkvk/models/res_config_settings.py
odoo/addons/l10n_nl_openkvk/readme/CONFIGURE.rst
odoo/addons/l10n_nl_openkvk/readme/CONTRIBUTORS.rst
odoo/addons/l10n_nl_openkvk/readme/DESCRIPTION.rst
odoo/addons/l10n_nl_openkvk/readme/USAGE.rst
odoo/addons/l10n_nl_openkvk/static/description/icon.png
odoo/addons/l10n_nl_openkvk/static/description/index.html
odoo/addons/l10n_nl_openkvk/tests/__init__.py
odoo/addons/l10n_nl_openkvk/tests/test_l10n_nl_openkvk.py
odoo/addons/l10n_nl_openkvk/views/res_config_settings.xml
odoo/addons/l10n_nl_openkvk/wizards/__init__.py
odoo/addons/l10n_nl_openkvk/wizards/l10n_nl_kvk_preview_wizard.py
odoo11_addon_l10n_nl_openkvk-11.0.1.0.0.99.dev5.dist-info/METADATA
odoo11_addon_l10n_nl_openkvk-11.0.1.0.0.99.dev5.dist-info/WHEEL
odoo11_addon_l10n_nl_openkvk-11.0.1.0.0.99.dev5.dist-info/top_level.txt
odoo11_addon_l10n_nl_openkvk-11.0.1.0.0.99.dev5.dist-info/RECORD
